pyqbdl.cpython-37m-x86_64-linux-gnu.so
pyqbdl-0.1.0.dist-info/RECORD
pyqbdl-0.1.0.dist-info/METADATA
pyqbdl-0.1.0.dist-info/top_level.txt
pyqbdl-0.1.0.dist-info/WHEEL
